[{"locality_id":9,"locality_name":"Kiongo Kidogo"},{"locality_id":23,"locality_name":"Donge Majenzi"},{"locality_id":35,"locality_name":"Mcheza Shauri"},{"locality_id":47,"locality_name":"Chaani Mcheza Shauri"},{"locality_id":54,"locality_name":"Tumbatu Uvivini"},{"locality_id":55,"locality_name":"Jugakuu"},{"locality_id":56,"locality_name":"Donge mchangani"},{"locality_id":57,"locality_name":"Mbuyu Tende"},{"locality_id":61,"locality_name":"Tumbatu Jongowe"},{"locality_id":62,"locality_name":"Tumbatu Gomani"},{"locality_id":101,"locality_name":"Unguja Ukuu Tindini"},{"locality_id":102,"locality_name":"Ndijani Mwembepunda"},{"locality_id":104,"locality_name":"Kijibwemtu"},{"locality_id":105,"locality_name":"Cheju Zawiyani"},{"locality_id":120,"locality_name":"Muyuni 'C'"},{"locality_id":121,"locality_name":"Muyuni 'B'"},{"locality_id":122,"locality_name":"Muyuni 'A'"},{"locality_id":153,"locality_name":"C012"},{"locality_id":164,"locality_name":"Kiswandui"},{"locality_id":169,"locality_name":"Kwa Mtumwajeni"},{"locality_id":173,"locality_name":"Kwabintiamrani"},{"locality_id":187,"locality_name":"KisimaMajongoo"},{"locality_id":189,"locality_name":"Jangombe"},{"locality_id":203,"locality_name":"MuembeMajogoo"},{"locality_id":254,"locality_name":"Sharifumsa"},{"locality_id":260,"locality_name":"Mtopepo"},{"locality_id":265,"locality_name":"Kijogoo"},{"locality_id":281,"locality_name":"Wingwi Mtemani"},{"locality_id":290,"locality_name":"Kinowejiso"},{"locality_id":291,"locality_name":"Maziwa Ngombe"},{"locality_id":298,"locality_name":"Mzambaru takau"},{"locality_id":333,"locality_name":"Kisiwa Panza"},{"locality_id":337,"locality_name":"Muambe"},{"locality_id":343,"locality_name":"Tironi"},{"locality_id":349,"locality_name":"Mzingani"},{"locality_id":381,"locality_name":"Chinga"},{"locality_id":385,"locality_name":"Misingini"}]